setup.py
Distribution_probability_functions.egg-info/PKG-INFO
Distribution_probability_functions.egg-info/SOURCES.txt
Distribution_probability_functions.egg-info/dependency_links.txt
Distribution_probability_functions.egg-info/top_level.txt
Distributions/BinomialDistribution.py
Distributions/GaussianDistribution.py
Distributions/GeneralDistributions.py
Distributions/__init__.py