Metadata-Version: 2.1
Name: Distribution-probability-functions
Version: 1.3
Summary: Distribution functions
Home-page: UNKNOWN
Author: Birhane Kahsay
Author-email: birhane.kahsay99@gmail.com
License: UNKNOWN
Platform: UNKNOWN
